brain_games/__init__.py
brain_games/cli.py
brain_games/game_engine.py
brain_games/games/calc.py
brain_games/games/even.py
brain_games/games/gcd.py
brain_games/games/prime.py
brain_games/games/progression.py
brain_games/scripts/__init__.py
brain_games/scripts/brain_calc.py
brain_games/scripts/brain_even.py
brain_games/scripts/brain_games.py
brain_games/scripts/brain_gcd.py
brain_games/scripts/brain_prime.py
brain_games/scripts/brain_progression.py
hexlet_code_dddarknight-0.1.0.dist-info/entry_points.txt
hexlet_code_dddarknight-0.1.0.dist-info/WHEEL
hexlet_code_dddarknight-0.1.0.dist-info/METADATA
hexlet_code_dddarknight-0.1.0.dist-info/RECORD
