Metadata-Version: 2.1
Name: hexlet-code-dddarknight
Version: 0.1.0
Summary: Provides oppotunity to play games with mathematical calculations. In version 0.1.0 there are 5 games: calculations of two numbers, identification of an even number, finding the greatest common divisor of given numbers, identification of a prime number, finding missing number in the progression.
Home-page: https://github.com/Dddarknight/python-project-lvl1
License: GPL-3.0-only
Keywords: game,random,randint
Author: Dddarknight
Author-email: 9801677@gmail.com
Requires-Python: >=3.8.10,<4.0.0
Classifier: License :: OSI Approved :: GNU General Public License v3 (GPLv3)
Classifier: Programming Language :: Python :: 3
Classifier: Programming Language :: Python :: 3.10
Classifier: Programming Language :: Python :: 3.9
Classifier: Topic :: Games/Entertainment
Requires-Dist: prompt (>=0.4.1,<0.5.0)
Project-URL: Repository, https://github.com/Dddarknight/python-project-lvl1
